httpxy.py
httpxy-0.0.0a1.dist-info/LICENSE
httpxy-0.0.0a1.dist-info/WHEEL
httpxy-0.0.0a1.dist-info/METADATA
httpxy-0.0.0a1.dist-info/RECORD
