Metadata-Version: 2.1
Name: httpxy
Version: 0.0.0a1
Summary: HTTP client (httpx) with native yaml support.
Home-page: https://github.com/Kilo59/httpxy
Author: Gabriel
Author-email: gabriel59kg@gmail.com
Requires-Python: >=3.6.1,<4.0.0
Classifier: Development Status :: 1 - Planning
Classifier: Environment :: Web Environment
Classifier: Framework :: AsyncIO
Classifier: Framework :: Trio
Classifier: Intended Audience :: Developers
Classifier: License :: OSI Approved :: BSD License
Classifier: Operating System :: OS Independent
Classifier: Programming Language :: Python :: 3
Classifier: Programming Language :: Python :: 3 :: Only
Classifier: Programming Language :: Python :: 3.6
Classifier: Programming Language :: Python :: 3.7
Classifier: Programming Language :: Python :: 3.8
Classifier: Programming Language :: Python :: 3.9
Classifier: Topic :: Internet :: WWW/HTTP
Provides-Extra: brotli
Provides-Extra: http2
Requires-Dist: PyYAML (>=5.4.1,<6.0.0)
Requires-Dist: httpx (>=0.17,<0.18)
Project-URL: Repository, https://github.com/Kilo59/httpxy
